[
   {
      "channel": 9001,
      "domain": 1,
      "detType": 1,
      "serial": "sumCore1",
      "TimeOffset": 0.0,
      "theta": 0,
      "phi": 0,
      "threshold": 25,
      "cs_dom": 0,
      "enable": 1,
      "pol_order": 2,
      "pol_list": [
         0,
         1
      ],
      "on": 1
   },
   {
      "channel": 9002,
      "domain": 2,
      "detType": 2,
      "serial": "sumSEG",
      "TimeOffset": 0.0,
      "theta": 0,
      "phi": 0,
      "threshold": 25,
      "cs_dom": 0,
      "enable": 1,
      "pol_order": 2,
      "pol_list": [
         0,
         1
      ],
      "on": 1
   },
   {
      "channel": 9003,
      "domain": 3,
      "detType": 3,
      "serial": "sumLaBr",
      "TimeOffset": 0.0,
      "theta": 0,
      "phi": 0,
      "threshold": 25,
      "cs_dom": 0,
      "enable": 1,
      "pol_order": 2,
      "pol_list": [
         0,
         1
      ],
      "on": 1
   },
   {
      "channel": 9001,
      "domain": 1,
      "detType": 1,
      "serial": "sumCore1",
      "TimeOffset": 0.0,
      "theta": 0,
      "phi": 0,
      "threshold": 25,
      "cs_dom": 0,
      "enable": 1,
      "pol_order": 2,
      "pol_list": [
         0,
         1
      ],
      "on": 1
   },
   {
      "channel": 2,
      "domain": 101,
      "detType": 2,
      "serial": "CL35B",
      "TimeOffset": 0.0,
      "theta": 90,
      "phi": 0,
      "threshold": 25,
      "cs_dom": 0,
      "enable": 1,
      "pol_order": 2,
      "pol_list": [
         3.1988,
         1.332274
      ],
      "on": 1
   },
   {
      "channel": 3,
      "domain": 102,
      "detType": 2,
      "serial": "CL35B",
      "TimeOffset": 0.0,
      "theta": 90,
      "phi": 0,
      "threshold": 10,
      "cs_dom": 0,
      "enable": 1,
      "pol_order": 2,
      "pol_list": [
         1.161,
         1.319821
      ],
      "on": 1
   },
   {
      "channel": 4,
      "domain": 103,
      "detType": 2,
      "serial": "CL35B",
      "TimeOffset": 0.0,
      "theta": 90,
      "phi": 0,
      "threshold": 10,
      "cs_dom": 0,
      "enable": 1,
      "pol_order": 2,
      "pol_list": [
         -0.4132,
         1.348444
      ],
      "on": 1
   },
   {
      "channel": 5,
      "domain": 104,
      "detType": 2,
      "serial": "CL35B",
      "TimeOffset": 0.0,
      "theta": 90,
      "phi": 0,
      "threshold": 22,
      "cs_dom": 0,
      "enable": 1,
      "pol_order": 2,
      "pol_list": [
         -2.4054,
         1.330113
      ],
      "on": 1
   },
   {
      "channel": 6,
      "domain": 105,
      "detType": 2,
      "serial": "CL35B",
      "TimeOffset": 0.0,
      "theta": 90,
      "phi": 0,
      "threshold": 15,
      "cs_dom": 0,
      "enable": 1,
      "pol_order": 2,
      "pol_list": [
         -1.1488,
         1.296314
      ],
      "on": 1
   },
   {
      "channel": 7,
      "domain": 106,
      "detType": 2,
      "serial": "CL35B",
      "TimeOffset": 0.0,
      "theta": 90,
      "phi": 0,
      "threshold": 15,
      "cs_dom": 0,
      "enable": 1,
      "pol_order": 2,
      "pol_list": [
         -1.1674,
         1.329158
      ],
      "on": 1
   },
   {
      "channel": 8,
      "domain": 107,
      "detType": 2,
      "serial": "CL35B",
      "TimeOffset": 0.0,
      "theta": 90,
      "phi": 0,
      "threshold": 15,
      "cs_dom": 0,
      "enable": 1,
      "pol_order": 2,
      "pol_list": [
         2.311,
         1.314615
      ],
      "on": 1
   },
   {
      "channel": 9,
      "domain": 108,
      "detType": 2,
      "serial": "CL35B",
      "TimeOffset": 0.0,
      "theta": 90,
      "phi": 0,
      "threshold": 18,
      "cs_dom": 0,
      "enable": 1,
      "pol_order": 2,
      "pol_list": [
         2.0294,
         1.301218
      ],
      "on": 1
   },
   {
      "channel": 0,
      "domain": 109,
      "detType": 1,
      "serial": "CL35B",
      "TimeOffset": 0.0,
      "theta": 90,
      "phi": 0,
      "threshold": 10,
      "cs_dom": 0,
      "enable": 1,
      "pol_order": 2,
      "pol_list": [
         1.2391,
         1.337121
      ],
      "on": 1
   },
   {
      "channel": 1,
      "domain": 110,
      "detType": 10,
      "serial": "CL35B",
      "TimeOffset": 0.0,
      "theta": 90,
      "phi": 0,
      "threshold": 10,
      "cs_dom": 0,
      "enable": 1,
      "pol_order": 2,
      "pol_list": [
         -5.1806,
         3.730905
      ],
      "on": 1
   },
   {
      "channel": 102,
      "domain": 111,
      "detType": 2,
      "serial": "CL35G",
      "TimeOffset": 0.0,
      "theta": 90,
      "phi": 0,
      "threshold": 12,
      "cs_dom": 0,
      "enable": 1,
      "pol_order": 2,
      "pol_list": [
         -2.2313,
         1.343794
      ],
      "on": 1
   },
   {
      "channel": 103,
      "domain": 112,
      "detType": 2,
      "serial": "CL35G",
      "TimeOffset": 0.0,
      "theta": 90,
      "phi": 0,
      "threshold": 14,
      "cs_dom": 0,
      "enable": 1,
      "pol_order": 2,
      "pol_list": [
         0.7804,
         1.342955
      ],
      "on": 1
   },
   {
      "channel": 104,
      "domain": 113,
      "detType": 2,
      "serial": "CL35G",
      "TimeOffset": 0.0,
      "theta": 90,
      "phi": 0,
      "threshold": 17,
      "cs_dom": 0,
      "enable": 1,
      "pol_order": 2,
      "pol_list": [
         0.5418,
         1.297665
      ],
      "on": 1
   },
   {
      "channel": 105,
      "domain": 114,
      "detType": 2,
      "serial": "CL35G",
      "TimeOffset": 0.0,
      "theta": 90,
      "phi": 0,
      "threshold": 16,
      "cs_dom": 0,
      "enable": 1,
      "pol_order": 2,
      "pol_list": [
         0.4843,
         1.281154
      ],
      "on": 1
   },
   {
      "channel": 106,
      "domain": 115,
      "detType": 2,
      "serial": "CL35G",
      "TimeOffset": 0.0,
      "theta": 90,
      "phi": 0,
      "threshold": 20,
      "cs_dom": 0,
      "enable": 1,
      "pol_order": 2,
      "pol_list": [
         0.3161,
         1.375438
      ],
      "on": 1
   },
   {
      "channel": 107,
      "domain": 116,
      "detType": 2,
      "serial": "CL35G",
      "TimeOffset": 0.0,
      "theta": 90,
      "phi": 0,
      "threshold": 15,
      "cs_dom": 0,
      "enable": 1,
      "pol_order": 2,
      "pol_list": [
         -6.7397,
         1.39625
      ],
      "on": 1
   },
   {
      "channel": 108,
      "domain": 117,
      "detType": 2,
      "serial": "CL35G",
      "TimeOffset": 0.0,
      "theta": 90,
      "phi": 0,
      "threshold": 14,
      "cs_dom": 0,
      "enable": 1,
      "pol_order": 2,
      "pol_list": [
         -3.912,
         1.34696
      ],
      "on": 1
   },
   {
      "channel": 109,
      "domain": 118,
      "detType": 2,
      "serial": "CL35G",
      "TimeOffset": 0.0,
      "theta": 90,
      "phi": 0,
      "threshold": 12,
      "cs_dom": 0,
      "enable": 1,
      "pol_order": 2,
      "pol_list": [
         -1.9955,
         1.286466
      ],
      "on": 1
   },
   {
      "channel": 100,
      "domain": 119,
      "detType": 1,
      "serial": "CL35G",
      "TimeOffset": 0.0,
      "theta": 90,
      "phi": 0,
      "threshold": 20,
      "cs_dom": 0,
      "enable": 1,
      "pol_order": 2,
      "pol_list": [
         1.8146,
         1.245367
      ],
      "on": 1
   },
   {
      "channel": 101,
      "domain": 120,
      "detType": 10,
      "serial": "CL35G",
      "TimeOffset": 0.0,
      "theta": 90,
      "phi": 0,
      "threshold": 20,
      "cs_dom": 0,
      "enable": 1,
      "pol_order": 2,
      "pol_list": [
         2.0709,
         3.764127
      ],
      "on": 1
   },
   {
      "channel": 202,
      "domain": 121,
      "detType": 2,
      "serial": "CL35R",
      "TimeOffset": 0.0,
      "theta": 90,
      "phi": 0,
      "threshold": 16,
      "cs_dom": 0,
      "enable": 1,
      "pol_order": 2,
      "pol_list": [
         -1.7306,
         1.327602
      ],
      "on": 1
   },
   {
      "channel": 203,
      "domain": 122,
      "detType": 2,
      "serial": "CL35R",
      "TimeOffset": 0.0,
      "theta": 90,
      "phi": 0,
      "threshold": 19,
      "cs_dom": 0,
      "enable": 1,
      "pol_order": 2,
      "pol_list": [
         -1.3659,
         1.364238
      ],
      "on": 1
   },
   {
      "channel": 204,
      "domain": 123,
      "detType": 2,
      "serial": "CL35R",
      "TimeOffset": 0.0,
      "theta": 90,
      "phi": 0,
      "threshold": 14,
      "cs_dom": 0,
      "enable": 1,
      "pol_order": 2,
      "pol_list": [
         0.7892,
         1.366714
      ],
      "on": 1
   },
   {
      "channel": 205,
      "domain": 124,
      "detType": 2,
      "serial": "CL35R",
      "TimeOffset": 0.0,
      "theta": 90,
      "phi": 0,
      "threshold": 15,
      "cs_dom": 0,
      "enable": 1,
      "pol_order": 2,
      "pol_list": [
         3.2938,
         1.371558
      ],
      "on": 1
   },
   {
      "channel": 206,
      "domain": 125,
      "detType": 2,
      "serial": "CL35R",
      "TimeOffset": 0.0,
      "theta": 90,
      "phi": 0,
      "threshold": 15,
      "cs_dom": 0,
      "enable": 1,
      "pol_order": 2,
      "pol_list": [
         4.4127,
         1.33774
      ],
      "on": 1
   },
   {
      "channel": 207,
      "domain": 126,
      "detType": 2,
      "serial": "CL35R",
      "TimeOffset": 0.0,
      "theta": 90,
      "phi": 0,
      "threshold": 15,
      "cs_dom": 0,
      "enable": 1,
      "pol_order": 2,
      "pol_list": [
         4.027,
         1.305013
      ],
      "on": 1
   },
   {
      "channel": 208,
      "domain": 127,
      "detType": 2,
      "serial": "CL35R",
      "TimeOffset": 0.0,
      "theta": 90,
      "phi": 0,
      "threshold": 15,
      "cs_dom": 0,
      "enable": 1,
      "pol_order": 2,
      "pol_list": [
         0.264,
         1.3596
      ],
      "on": 1
   },
   {
      "channel": 209,
      "domain": 128,
      "detType": 2,
      "serial": "CL35R",
      "TimeOffset": 0.0,
      "theta": 90,
      "phi": 0,
      "threshold": 15,
      "cs_dom": 0,
      "enable": 1,
      "pol_order": 2,
      "pol_list": [
         0.264,
         1.290825
      ],
      "on": 1
   },
   {
      "channel": 200,
      "domain": 129,
      "detType": 1,
      "serial": "CL35R",
      "TimeOffset": 0.0,
      "theta": 90,
      "phi": 0,
      "threshold": 11,
      "cs_dom": 0,
      "enable": 1,
      "pol_order": 2,
      "pol_list": [
         1.0207,
         1.33292
      ],
      "on": 1
   },
   {
      "channel": 201,
      "domain": 130,
      "detType": 10,
      "serial": "CL35R",
      "TimeOffset": 0.0,
      "theta": 90,
      "phi": 0,
      "threshold": 10,
      "cs_dom": 0,
      "enable": 1,
      "pol_order": 2,
      "pol_list": [
         1.4959,
         3.794582
      ],
      "on": 1
   },
   {
      "channel": 302,
      "domain": 131,
      "detType": 2,
      "serial": "CL35W",
      "TimeOffset": 0.0,
      "theta": 90,
      "phi": 0,
      "threshold": 15,
      "cs_dom": 0,
      "enable": 1,
      "pol_order": 2,
      "pol_list": [
         6.4133,
         1.307947
      ],
      "on": 1
   },
   {
      "channel": 303,
      "domain": 132,
      "detType": 2,
      "serial": "CL35W",
      "TimeOffset": 0.0,
      "theta": 90,
      "phi": 0,
      "threshold": 15,
      "cs_dom": 0,
      "enable": 1,
      "pol_order": 2,
      "pol_list": [
         0.6957,
         1.28378
      ],
      "on": 1
   },
   {
      "channel": 304,
      "domain": 133,
      "detType": 2,
      "serial": "CL35W",
      "TimeOffset": 0.0,
      "theta": 90,
      "phi": 0,
      "threshold": 15,
      "cs_dom": 0,
      "enable": 1,
      "pol_order": 2,
      "pol_list": [
         0.8338,
         1.247688
      ],
      "on": 1
   },
   {
      "channel": 305,
      "domain": 134,
      "detType": 2,
      "serial": "CL35W",
      "TimeOffset": 0.0,
      "theta": 90,
      "phi": 0,
      "threshold": 15,
      "cs_dom": 0,
      "enable": 1,
      "pol_order": 2,
      "pol_list": [
         1.2743,
         1.312635
      ],
      "on": 1
   },
   {
      "channel": 306,
      "domain": 135,
      "detType": 2,
      "serial": "CL35W",
      "TimeOffset": 0.0,
      "theta": 90,
      "phi": 0,
      "threshold": 15,
      "cs_dom": 0,
      "enable": 1,
      "pol_order": 2,
      "pol_list": [
         0.6899,
         1.342733
      ],
      "on": 1
   },
   {
      "channel": 307,
      "domain": 136,
      "detType": 2,
      "serial": "CL35W",
      "TimeOffset": 0.0,
      "theta": 90,
      "phi": 0,
      "threshold": 15,
      "cs_dom": 0,
      "enable": 1,
      "pol_order": 2,
      "pol_list": [
         0.6325,
         1.290929
      ],
      "on": 1
   },
   {
      "channel": 308,
      "domain": 137,
      "detType": 2,
      "serial": "CL35W",
      "TimeOffset": 0.0,
      "theta": 90,
      "phi": 0,
      "threshold": 15,
      "cs_dom": 0,
      "enable": 1,
      "pol_order": 2,
      "pol_list": [
         -0.2121,
         1.34951
      ],
      "on": 1
   },
   {
      "channel": 309,
      "domain": 138,
      "detType": 2,
      "serial": "CL35W",
      "TimeOffset": 0.0,
      "theta": 90,
      "phi": 0,
      "threshold": 15,
      "cs_dom": 0,
      "enable": 1,
      "pol_order": 2,
      "pol_list": [
         1.0886,
         1.299055
      ],
      "on": 1
   },
   {
      "channel": 300,
      "domain": 139,
      "detType": 1,
      "serial": "CL35W",
      "TimeOffset": 0.0,
      "theta": 90,
      "phi": 0,
      "threshold": 15,
      "cs_dom": 0,
      "enable": 1,
      "pol_order": 2,
      "pol_list": [
         2.3302,
         1.300476
      ],
      "on": 1
   },
   {
      "channel": 301,
      "domain": 140,
      "detType": 10,
      "serial": "CL35W",
      "TimeOffset": 0.0,
      "theta": 90,
      "phi": 0,
      "threshold": 10,
      "cs_dom": 0,
      "enable": 1,
      "pol_order": 2,
      "pol_list": [
         16.9278,
         3.581009
      ],
      "on": 1
   }
]
