[
   {
      "channel": 9001,
      "domain": 1,
      "detType": 1,
      "serial": "sumCore1",
      "TimeOffset": 0.0,
      "theta": 0,
      "phi": 0,
      "threshold": 25,
      "cs_dom": 0,
      "enable": 1,
      "pol_order": 2,
      "pol_list": [
         0,
         1
      ],
      "on": 1
   },
   {
      "channel": 9002,
      "domain": 2,
      "detType": 2,
      "serial": "sumSEG",
      "TimeOffset": 0.0,
      "theta": 0,
      "phi": 0,
      "threshold": 25,
      "cs_dom": 0,
      "enable": 1,
      "pol_order": 2,
      "pol_list": [
         0,
         1
      ],
      "on": 1
   },
   {
      "channel": 9003,
      "domain": 3,
      "detType": 3,
      "serial": "sumLaBr",
      "TimeOffset": 0.0,
      "theta": 0,
      "phi": 0,
      "threshold": 25,
      "cs_dom": 0,
      "enable": 1,
      "pol_order": 2,
      "pol_list": [
         0,
         1
      ],
      "on": 1
   },
   {
      "channel": 9001,
      "domain": 1,
      "detType": 1,
      "serial": "sumCore1",
      "TimeOffset": 0.0,
      "theta": 0,
      "phi": 0,
      "threshold": 25,
      "cs_dom": 0,
      "enable": 1,
      "pol_order": 2,
      "pol_list": [
         0,
         1
      ],
      "on": 1
   },
   {
      "channel": 2,
      "domain": 101,
      "detType": 2,
      "serial": "CL30B",
      "TimeOffset": 0.0,
      "theta": 90,
      "phi": 0,
      "threshold": 25,
      "cs_dom": 0,
      "enable": 1,
      "pol_order": 2,
      "pol_list": [
         4.517,
         1.337584
      ],
      "on": 1
   },
   {
      "channel": 3,
      "domain": 102,
      "detType": 2,
      "serial": "CL30B",
      "TimeOffset": 0.0,
      "theta": 90,
      "phi": 0,
      "threshold": 10,
      "cs_dom": 0,
      "enable": 1,
      "pol_order": 2,
      "pol_list": [
         0.9631,
         1.327317
      ],
      "on": 1
   },
   {
      "channel": 4,
      "domain": 103,
      "detType": 2,
      "serial": "CL30B",
      "TimeOffset": 0.0,
      "theta": 90,
      "phi": 0,
      "threshold": 10,
      "cs_dom": 0,
      "enable": 1,
      "pol_order": 2,
      "pol_list": [
         0.058,
         1.355008
      ],
      "on": 1
   },
   {
      "channel": 5,
      "domain": 104,
      "detType": 2,
      "serial": "CL30B",
      "TimeOffset": 0.0,
      "theta": 90,
      "phi": 0,
      "threshold": 22,
      "cs_dom": 0,
      "enable": 1,
      "pol_order": 2,
      "pol_list": [
         -0.8633,
         1.341248
      ],
      "on": 1
   },
   {
      "channel": 6,
      "domain": 105,
      "detType": 2,
      "serial": "CL30B",
      "TimeOffset": 0.0,
      "theta": 90,
      "phi": 0,
      "threshold": 15,
      "cs_dom": 0,
      "enable": 1,
      "pol_order": 2,
      "pol_list": [
         -0.041,
         1.303412
      ],
      "on": 1
   },
   {
      "channel": 7,
      "domain": 106,
      "detType": 2,
      "serial": "CL30B",
      "TimeOffset": 0.0,
      "theta": 90,
      "phi": 0,
      "threshold": 15,
      "cs_dom": 0,
      "enable": 1,
      "pol_order": 2,
      "pol_list": [
         1.417,
         1.333865
      ],
      "on": 1
   },
   {
      "channel": 8,
      "domain": 107,
      "detType": 2,
      "serial": "CL30B",
      "TimeOffset": 0.0,
      "theta": 90,
      "phi": 0,
      "threshold": 15,
      "cs_dom": 0,
      "enable": 1,
      "pol_order": 2,
      "pol_list": [
         0.7393,
         1.320048
      ],
      "on": 1
   },
   {
      "channel": 9,
      "domain": 108,
      "detType": 2,
      "serial": "CL30B",
      "TimeOffset": 0.0,
      "theta": 90,
      "phi": 0,
      "threshold": 18,
      "cs_dom": 0,
      "enable": 1,
      "pol_order": 2,
      "pol_list": [
         0.4178,
         1.308822
      ],
      "on": 1
   },
   {
      "channel": 0,
      "domain": 109,
      "detType": 1,
      "serial": "CL30B",
      "TimeOffset": 0.0,
      "theta": 90,
      "phi": 0,
      "threshold": 10,
      "cs_dom": 0,
      "enable": 1,
      "pol_order": 2,
      "pol_list": [
         1.3754,
         1.339183
      ],
      "on": 1
   },
   {
      "channel": 1,
      "domain": 110,
      "detType": 10,
      "serial": "CL30B",
      "TimeOffset": 0.0,
      "theta": 90,
      "phi": 0,
      "threshold": 10,
      "cs_dom": 0,
      "enable": 1,
      "pol_order": 2,
      "pol_list": [
         -5.1806,
         3.730905
      ],
      "on": 1
   },
   {
      "channel": 102,
      "domain": 111,
      "detType": 2,
      "serial": "CL30G",
      "TimeOffset": 0.0,
      "theta": 90,
      "phi": 0,
      "threshold": 12,
      "cs_dom": 0,
      "enable": 1,
      "pol_order": 2,
      "pol_list": [
         -1.8425,
         1.34931
      ],
      "on": 1
   },
   {
      "channel": 103,
      "domain": 112,
      "detType": 2,
      "serial": "CL30G",
      "TimeOffset": 0.0,
      "theta": 90,
      "phi": 0,
      "threshold": 14,
      "cs_dom": 0,
      "enable": 1,
      "pol_order": 2,
      "pol_list": [
         0.4023,
         1.347993
      ],
      "on": 1
   },
   {
      "channel": 104,
      "domain": 113,
      "detType": 2,
      "serial": "CL30G",
      "TimeOffset": 0.0,
      "theta": 90,
      "phi": 0,
      "threshold": 17,
      "cs_dom": 0,
      "enable": 1,
      "pol_order": 2,
      "pol_list": [
         -0.7759,
         1.305669
      ],
      "on": 1
   },
   {
      "channel": 105,
      "domain": 114,
      "detType": 2,
      "serial": "CL30G",
      "TimeOffset": 0.0,
      "theta": 90,
      "phi": 0,
      "threshold": 16,
      "cs_dom": 0,
      "enable": 1,
      "pol_order": 2,
      "pol_list": [
         -0.2018,
         1.290443
      ],
      "on": 1
   },
   {
      "channel": 106,
      "domain": 115,
      "detType": 2,
      "serial": "CL30G",
      "TimeOffset": 0.0,
      "theta": 90,
      "phi": 0,
      "threshold": 20,
      "cs_dom": 0,
      "enable": 1,
      "pol_order": 2,
      "pol_list": [
         0.6201,
         1.381388
      ],
      "on": 1
   },
   {
      "channel": 107,
      "domain": 116,
      "detType": 2,
      "serial": "CL30G",
      "TimeOffset": 0.0,
      "theta": 90,
      "phi": 0,
      "threshold": 15,
      "cs_dom": 0,
      "enable": 1,
      "pol_order": 2,
      "pol_list": [
         2.0186,
         1.392413
      ],
      "on": 1
   },
   {
      "channel": 108,
      "domain": 117,
      "detType": 2,
      "serial": "CL30G",
      "TimeOffset": 0.0,
      "theta": 90,
      "phi": 0,
      "threshold": 14,
      "cs_dom": 0,
      "enable": 1,
      "pol_order": 2,
      "pol_list": [
         -3.4042,
         1.35171
      ],
      "on": 1
   },
   {
      "channel": 109,
      "domain": 118,
      "detType": 2,
      "serial": "CL30G",
      "TimeOffset": 0.0,
      "theta": 90,
      "phi": 0,
      "threshold": 12,
      "cs_dom": 0,
      "enable": 1,
      "pol_order": 2,
      "pol_list": [
         -1.5179,
         1.294081
      ],
      "on": 1
   },
   {
      "channel": 100,
      "domain": 119,
      "detType": 1,
      "serial": "CL30G",
      "TimeOffset": 0.0,
      "theta": 90,
      "phi": 0,
      "threshold": 20,
      "cs_dom": 0,
      "enable": 1,
      "pol_order": 2,
      "pol_list": [
         1.8888,
         1.247796
      ],
      "on": 1
   },
   {
      "channel": 101,
      "domain": 120,
      "detType": 10,
      "serial": "CL30G",
      "TimeOffset": 0.0,
      "theta": 90,
      "phi": 0,
      "threshold": 20,
      "cs_dom": 0,
      "enable": 1,
      "pol_order": 2,
      "pol_list": [
         2.0709,
         3.764127
      ],
      "on": 1
   },
   {
      "channel": 202,
      "domain": 121,
      "detType": 2,
      "serial": "CL30R",
      "TimeOffset": 0.0,
      "theta": 90,
      "phi": 0,
      "threshold": 16,
      "cs_dom": 0,
      "enable": 1,
      "pol_order": 2,
      "pol_list": [
         -0.9214,
         1.331483
      ],
      "on": 1
   },
   {
      "channel": 203,
      "domain": 122,
      "detType": 2,
      "serial": "CL30R",
      "TimeOffset": 0.0,
      "theta": 90,
      "phi": 0,
      "threshold": 19,
      "cs_dom": 0,
      "enable": 1,
      "pol_order": 2,
      "pol_list": [
         -1.417,
         1.372925
      ],
      "on": 1
   },
   {
      "channel": 204,
      "domain": 123,
      "detType": 2,
      "serial": "CL30R",
      "TimeOffset": 0.0,
      "theta": 90,
      "phi": 0,
      "threshold": 14,
      "cs_dom": 0,
      "enable": 1,
      "pol_order": 2,
      "pol_list": [
         1.8801,
         1.372225
      ],
      "on": 1
   },
   {
      "channel": 205,
      "domain": 124,
      "detType": 2,
      "serial": "CL30R",
      "TimeOffset": 0.0,
      "theta": 90,
      "phi": 0,
      "threshold": 15,
      "cs_dom": 0,
      "enable": 1,
      "pol_order": 2,
      "pol_list": [
         3.2998,
         1.38378
      ],
      "on": 1
   },
   {
      "channel": 206,
      "domain": 125,
      "detType": 2,
      "serial": "CL30R",
      "TimeOffset": 0.0,
      "theta": 90,
      "phi": 0,
      "threshold": 15,
      "cs_dom": 0,
      "enable": 1,
      "pol_order": 2,
      "pol_list": [
         5.5748,
         1.342271
      ],
      "on": 1
   },
   {
      "channel": 207,
      "domain": 126,
      "detType": 2,
      "serial": "CL30R",
      "TimeOffset": 0.0,
      "theta": 90,
      "phi": 0,
      "threshold": 15,
      "cs_dom": 0,
      "enable": 1,
      "pol_order": 2,
      "pol_list": [
         2.483,
         1.315015
      ],
      "on": 1
   },
   {
      "channel": 208,
      "domain": 127,
      "detType": 2,
      "serial": "CL30R",
      "TimeOffset": 0.0,
      "theta": 90,
      "phi": 0,
      "threshold": 15,
      "cs_dom": 0,
      "enable": 1,
      "pol_order": 2,
      "pol_list": [
         -0.9037,
         1.366174
      ],
      "on": 1
   },
   {
      "channel": 209,
      "domain": 128,
      "detType": 2,
      "serial": "CL30R",
      "TimeOffset": 0.0,
      "theta": 90,
      "phi": 0,
      "threshold": 15,
      "cs_dom": 0,
      "enable": 1,
      "pol_order": 2,
      "pol_list": [
         -0.1742,
         1.298345
      ],
      "on": 1
   },
   {
      "channel": 200,
      "domain": 129,
      "detType": 1,
      "serial": "CL30R",
      "TimeOffset": 0.0,
      "theta": 90,
      "phi": 0,
      "threshold": 11,
      "cs_dom": 0,
      "enable": 1,
      "pol_order": 2,
      "pol_list": [
         -0.4807,
         1.335333
      ],
      "on": 1
   },
   {
      "channel": 201,
      "domain": 130,
      "detType": 10,
      "serial": "CL30R",
      "TimeOffset": 0.0,
      "theta": 90,
      "phi": 0,
      "threshold": 10,
      "cs_dom": 0,
      "enable": 1,
      "pol_order": 2,
      "pol_list": [
         1.4959,
         3.794582
      ],
      "on": 1
   },
   {
      "channel": 302,
      "domain": 131,
      "detType": 2,
      "serial": "CL30W",
      "TimeOffset": 0.0,
      "theta": 90,
      "phi": 0,
      "threshold": 15,
      "cs_dom": 0,
      "enable": 1,
      "pol_order": 2,
      "pol_list": [
         5.7623,
         1.316242
      ],
      "on": 1
   },
   {
      "channel": 303,
      "domain": 132,
      "detType": 2,
      "serial": "CL30W",
      "TimeOffset": 0.0,
      "theta": 90,
      "phi": 0,
      "threshold": 15,
      "cs_dom": 0,
      "enable": 1,
      "pol_order": 2,
      "pol_list": [
         0.5293,
         1.292725
      ],
      "on": 1
   },
   {
      "channel": 304,
      "domain": 133,
      "detType": 2,
      "serial": "CL30W",
      "TimeOffset": 0.0,
      "theta": 90,
      "phi": 0,
      "threshold": 15,
      "cs_dom": 0,
      "enable": 1,
      "pol_order": 2,
      "pol_list": [
         1.2937,
         1.254708
      ],
      "on": 1
   },
   {
      "channel": 305,
      "domain": 134,
      "detType": 2,
      "serial": "CL30W",
      "TimeOffset": 0.0,
      "theta": 90,
      "phi": 0,
      "threshold": 15,
      "cs_dom": 0,
      "enable": 1,
      "pol_order": 2,
      "pol_list": [
         1.3446,
         1.326239
      ],
      "on": 1
   },
   {
      "channel": 306,
      "domain": 135,
      "detType": 2,
      "serial": "CL30W",
      "TimeOffset": 0.0,
      "theta": 90,
      "phi": 0,
      "threshold": 15,
      "cs_dom": 0,
      "enable": 1,
      "pol_order": 2,
      "pol_list": [
         1.1938,
         1.349642
      ],
      "on": 1
   },
   {
      "channel": 307,
      "domain": 136,
      "detType": 2,
      "serial": "CL30W",
      "TimeOffset": 0.0,
      "theta": 90,
      "phi": 0,
      "threshold": 15,
      "cs_dom": 0,
      "enable": 1,
      "pol_order": 2,
      "pol_list": [
         0.183,
         1.304304
      ],
      "on": 1
   },
   {
      "channel": 308,
      "domain": 137,
      "detType": 2,
      "serial": "CL30W",
      "TimeOffset": 0.0,
      "theta": 90,
      "phi": 0,
      "threshold": 15,
      "cs_dom": 0,
      "enable": 1,
      "pol_order": 2,
      "pol_list": [
         1.646,
         1.36176
      ],
      "on": 1
   },
   {
      "channel": 309,
      "domain": 138,
      "detType": 2,
      "serial": "CL30W",
      "TimeOffset": 0.0,
      "theta": 90,
      "phi": 0,
      "threshold": 15,
      "cs_dom": 0,
      "enable": 1,
      "pol_order": 2,
      "pol_list": [
         1.6385,
         1.307648
      ],
      "on": 1
   },
   {
      "channel": 300,
      "domain": 139,
      "detType": 1,
      "serial": "CL30W",
      "TimeOffset": 0.0,
      "theta": 90,
      "phi": 0,
      "threshold": 15,
      "cs_dom": 0,
      "enable": 1,
      "pol_order": 2,
      "pol_list": [
         0.8021,
         1.311037
      ],
      "on": 1
   },
   {
      "channel": 301,
      "domain": 140,
      "detType": 10,
      "serial": "CL30W",
      "TimeOffset": 0.0,
      "theta": 90,
      "phi": 0,
      "threshold": 10,
      "cs_dom": 0,
      "enable": 1,
      "pol_order": 2,
      "pol_list": [
         16.9278,
         3.581009
      ],
      "on": 1
   }
]